Metadata-Version: 2.1
Name: odoo12-addon-sale_procurement_group_by_line
Version: 12.0.1.0.1
Summary: Base module for multiple procurement group by Sale order
Home-page: https://github.com/OCA/sale-workflow
Author: Camptocamp,Eficent,Serpent Consulting Services Pvt. Ltd.,Odoo Community Association (OCA)
Author-email: support@odoo-community.org
License: AGPL-3
Classifier: Programming Language :: Python
Classifier: Framework :: Odoo
Classifier: Framework :: Odoo :: 12.0
Classifier: License :: OSI Approved :: GNU Affero General Public License v3
Requires-Python: >=3.5
Requires-Dist: odoo<12.1dev,>=12.0a
